coverage.py
identify_comments.py
initi.py
override.py
params.py
recurse.py
tatuagem.py
tatuagem-0.1.1.dist-info/licenses/LICENSE
tatuagem-0.1.1.dist-info/METADATA
tatuagem-0.1.1.dist-info/WHEEL
tatuagem-0.1.1.dist-info/entry_points.txt
tatuagem-0.1.1.dist-info/top_level.txt
tatuagem-0.1.1.dist-info/RECORD
