Metadata-Version: 2.4
Name: tatuagem
Version: 0.1.1
Summary: A tool to generate ASCII art signatures (tattoos) and apply them to your code files recursively.
Author-email: Julian Henry <juliant@naver.com>, Derek Dickerson <derekdson67@gmail.com>
Maintainer-email: Julian Henry <juliant@naver.com>, Derek Dickerson <derekdson67@gmail.com>
Classifier: Programming Language :: Python :: 3
Classifier: License :: OSI Approved :: Apache Software License
Classifier: Operating System :: OS Independent
Requires-Python: >=3.12
License-File: LICENSE
Requires-Dist: Pillow
Requires-Dist: numpy
Dynamic: license-file
